{
  "meta": {
    "scope": "congressional",
    "contest_type": "governor",
    "year": 2025,
    "district_count": 11,
    "input_votes": 3426443,
    "matched_votes": 3423166,
    "direct_matched_votes": 3185324,
    "allocated_votes": 237842,
    "match_coverage_pct": 99.90436146172577,
    "direct_match_coverage_pct": 92.96299398530779
  },
  "general": {
    "results": {
      "1": {
        "dem_votes": 198958,
        "rep_votes": 186549,
        "other_votes": 0,
        "total_votes": 385507,
        "dem_candidate": "Abigail D. Spanberger",
        "rep_candidate": "Winsome Earle-Sears",
        "winner": "Democratic",
        "margin": 12409,
        "margin_pct": -3.218877997027291,
        "color": "#c6dbef"
      },
      "10": {
        "dem_votes": 185509,
        "rep_votes": 121593,
        "other_votes": 0,
        "total_votes": 307102,
        "dem_candidate": "Abigail D. Spanberger",
        "rep_candidate": "Winsome Earle-Sears",
        "winner": "Democratic",
        "margin": 63916,
        "margin_pct": -20.812629028791736,
        "color": "#3182bd"
      },
      "11": {
        "dem_votes": 229879,
        "rep_votes": 82074,
        "other_votes": 0,
        "total_votes": 311953,
        "dem_candidate": "Abigail D. Spanberger",
        "rep_candidate": "Winsome Earle-Sears",
        "winner": "Democratic",
        "margin": 147805,
        "margin_pct": -47.38053488826843,
        "color": "#08306b"
      },
      "2": {
        "dem_votes": 168440,
        "rep_votes": 144303,
        "other_votes": 0,
        "total_votes": 312743,
        "dem_candidate": "Abigail D. Spanberger",
        "rep_candidate": "Winsome Earle-Sears",
        "winner": "Democratic",
        "margin": 24137,
        "margin_pct": -7.717838608697876,
        "color": "#9ecae1"
      },
      "3": {
        "dem_votes": 172193,
        "rep_votes": 66964,
        "other_votes": 0,
        "total_votes": 239157,
        "dem_candidate": "Abigail D. Spanberger",
        "rep_candidate": "Winsome Earle-Sears",
        "winner": "Democratic",
        "margin": 105229,
        "margin_pct": -43.99996654917063,
        "color": "#08306b"
      },
      "4": {
        "dem_votes": 220435,
        "rep_votes": 93940,
        "other_votes": 0,
        "total_votes": 314375,
        "dem_candidate": "Abigail D. Spanberger",
        "rep_candidate": "Winsome Earle-Sears",
        "winner": "Democratic",
        "margin": 126495,
        "margin_pct": -40.23697813121272,
        "color": "#08306b"
      },
      "5": {
        "dem_votes": 158804,
        "rep_votes": 181259,
        "other_votes": 0,
        "total_votes": 340063,
        "dem_candidate": "Abigail D. Spanberger",
        "rep_candidate": "Winsome Earle-Sears",
        "winner": "Republican",
        "margin": 22455,
        "margin_pct": 6.603188232768634,
        "color": "#fb6a4a"
      },
      "6": {
        "dem_votes": 128986,
        "rep_votes": 180647,
        "other_votes": 0,
        "total_votes": 309633,
        "dem_candidate": "Abigail D. Spanberger",
        "rep_candidate": "Winsome Earle-Sears",
        "winner": "Republican",
        "margin": 51661,
        "margin_pct": 16.684591112704396,
        "color": "#ef3b2c"
      },
      "7": {
        "dem_votes": 174774,
        "rep_votes": 128545,
        "other_votes": 0,
        "total_votes": 303319,
        "dem_candidate": "Abigail D. Spanberger",
        "rep_candidate": "Winsome Earle-Sears",
        "winner": "Democratic",
        "margin": 46229,
        "margin_pct": -15.241049851806185,
        "color": "#6baed6"
      },
      "8": {
        "dem_votes": 244564,
        "rep_votes": 60756,
        "other_votes": 0,
        "total_votes": 305320,
        "dem_candidate": "Abigail D. Spanberger",
        "rep_candidate": "Winsome Earle-Sears",
        "winner": "Democratic",
        "margin": 183808,
        "margin_pct": -60.201755535176204,
        "color": "#08306b"
      },
      "9": {
        "dem_votes": 93024,
        "rep_votes": 200972,
        "other_votes": 0,
        "total_votes": 293996,
        "dem_candidate": "Abigail D. Spanberger",
        "rep_candidate": "Winsome Earle-Sears",
        "winner": "Republican",
        "margin": 107948,
        "margin_pct": 36.71750636063076,
        "color": "#a50f15"
      }
    }
  }
}