{
  "meta": {
    "scope": "congressional",
    "contest_type": "president",
    "year": 2024,
    "district_count": 11,
    "input_votes": 4505941,
    "matched_votes": 4505941,
    "direct_matched_votes": 4090021,
    "allocated_votes": 415920,
    "match_coverage_pct": 100.0,
    "direct_match_coverage_pct": 90.76951961865457
  },
  "general": {
    "results": {
      "1": {
        "dem_votes": 225112,
        "rep_votes": 243511,
        "other_votes": 8338,
        "total_votes": 476961,
        "dem_candidate": "Kamala D. Harris",
        "rep_candidate": "Donald J. Trump",
        "winner": "Republican",
        "margin": 18399,
        "margin_pct": 3.8575481014170974,
        "color": "#fcae91"
      },
      "10": {
        "dem_votes": 220060,
        "rep_votes": 183070,
        "other_votes": 13120,
        "total_votes": 416250,
        "dem_candidate": "Kamala D. Harris",
        "rep_candidate": "Donald J. Trump",
        "winner": "Democratic",
        "margin": 36990,
        "margin_pct": -8.886486486486486,
        "color": "#9ecae1"
      },
      "11": {
        "dem_votes": 268800,
        "rep_votes": 128344,
        "other_votes": 14881,
        "total_votes": 412025,
        "dem_candidate": "Kamala D. Harris",
        "rep_candidate": "Donald J. Trump",
        "winner": "Democratic",
        "margin": 140456,
        "margin_pct": -34.089193616892175,
        "color": "#08519c"
      },
      "2": {
        "dem_votes": 204293,
        "rep_votes": 204801,
        "other_votes": 6734,
        "total_votes": 415828,
        "dem_candidate": "Kamala D. Harris",
        "rep_candidate": "Donald J. Trump",
        "winner": "Republican",
        "margin": 508,
        "margin_pct": 0.12216589551449157,
        "color": "#f7f7f7"
      },
      "3": {
        "dem_votes": 212263,
        "rep_votes": 101976,
        "other_votes": 5607,
        "total_votes": 319846,
        "dem_candidate": "Kamala D. Harris",
        "rep_candidate": "Donald J. Trump",
        "winner": "Democratic",
        "margin": 110287,
        "margin_pct": -34.48128161677808,
        "color": "#08519c"
      },
      "4": {
        "dem_votes": 252200,
        "rep_votes": 132420,
        "other_votes": 6983,
        "total_votes": 391603,
        "dem_candidate": "Kamala D. Harris",
        "rep_candidate": "Donald J. Trump",
        "winner": "Democratic",
        "margin": 119780,
        "margin_pct": -30.58709969024752,
        "color": "#08519c"
      },
      "5": {
        "dem_votes": 190047,
        "rep_votes": 241311,
        "other_votes": 6287,
        "total_votes": 437645,
        "dem_candidate": "Kamala D. Harris",
        "rep_candidate": "Donald J. Trump",
        "winner": "Republican",
        "margin": 51264,
        "margin_pct": 11.713603491414275,
        "color": "#ef3b2c"
      },
      "6": {
        "dem_votes": 155248,
        "rep_votes": 253969,
        "other_votes": 6591,
        "total_votes": 415808,
        "dem_candidate": "Kamala D. Harris",
        "rep_candidate": "Donald J. Trump",
        "winner": "Republican",
        "margin": 98721,
        "margin_pct": 23.741967446513776,
        "color": "#cb181d"
      },
      "7": {
        "dem_votes": 204022,
        "rep_votes": 194171,
        "other_votes": 9220,
        "total_votes": 407413,
        "dem_candidate": "Kamala D. Harris",
        "rep_candidate": "Donald J. Trump",
        "winner": "Democratic",
        "margin": 9851,
        "margin_pct": -2.4179395355572844,
        "color": "#c6dbef"
      },
      "8": {
        "dem_votes": 289968,
        "rep_votes": 95876,
        "other_votes": 12893,
        "total_votes": 398737,
        "dem_candidate": "Kamala D. Harris",
        "rep_candidate": "Donald J. Trump",
        "winner": "Democratic",
        "margin": 194092,
        "margin_pct": -48.67669666973469,
        "color": "#08306b"
      },
      "9": {
        "dem_votes": 113383,
        "rep_votes": 295636,
        "other_votes": 4806,
        "total_votes": 413825,
        "dem_candidate": "Kamala D. Harris",
        "rep_candidate": "Donald J. Trump",
        "winner": "Republican",
        "margin": 182253,
        "margin_pct": 44.041080166737146,
        "color": "#67000d"
      }
    }
  }
}