{
  "meta": {
    "scope": "state_senate",
    "contest_type": "us_senate",
    "year": 2014,
    "district_count": 40,
    "input_votes": 2184520,
    "matched_votes": 2184520,
    "direct_matched_votes": 2048407,
    "allocated_votes": 136113,
    "match_coverage_pct": 100.0,
    "direct_match_coverage_pct": 93.76920330324282
  },
  "general": {
    "results": {
      "1": {
        "dem_votes": 17612,
        "rep_votes": 34128,
        "other_votes": 1456,
        "total_votes": 53196,
        "dem_candidate": "Mark Robert Warner",
        "rep_candidate": "Edward Walter Gillespie",
        "winner": "Republican",
        "margin": 16516,
        "margin_pct": 31.047447176479437,
        "color": "#a50f15"
      },
      "10": {
        "dem_votes": 24397,
        "rep_votes": 39804,
        "other_votes": 2051,
        "total_votes": 66252,
        "dem_candidate": "Mark Robert Warner",
        "rep_candidate": "Edward Walter Gillespie",
        "winner": "Republican",
        "margin": 15407,
        "margin_pct": 23.255147014429753,
        "color": "#cb181d"
      },
      "11": {
        "dem_votes": 33012,
        "rep_votes": 24925,
        "other_votes": 2177,
        "total_votes": 60114,
        "dem_candidate": "Mark Robert Warner",
        "rep_candidate": "Edward Walter Gillespie",
        "winner": "Democratic",
        "margin": 8087,
        "margin_pct": -13.452773064510762,
        "color": "#6baed6"
      },
      "12": {
        "dem_votes": 26016,
        "rep_votes": 39647,
        "other_votes": 2277,
        "total_votes": 67940,
        "dem_candidate": "Mark Robert Warner",
        "rep_candidate": "Edward Walter Gillespie",
        "winner": "Republican",
        "margin": 13631,
        "margin_pct": 20.063291139240505,
        "color": "#cb181d"
      },
      "13": {
        "dem_votes": 34230,
        "rep_votes": 19289,
        "other_votes": 1166,
        "total_votes": 54685,
        "dem_candidate": "Mark Robert Warner",
        "rep_candidate": "Edward Walter Gillespie",
        "winner": "Democratic",
        "margin": 14941,
        "margin_pct": -27.321934717015633,
        "color": "#3182bd"
      },
      "14": {
        "dem_votes": 41490,
        "rep_votes": 12218,
        "other_votes": 1826,
        "total_votes": 55534,
        "dem_candidate": "Mark Robert Warner",
        "rep_candidate": "Edward Walter Gillespie",
        "winner": "Democratic",
        "margin": 29272,
        "margin_pct": -52.710051499981994,
        "color": "#08306b"
      },
      "15": {
        "dem_votes": 27843,
        "rep_votes": 18041,
        "other_votes": 1401,
        "total_votes": 47285,
        "dem_candidate": "Mark Robert Warner",
        "rep_candidate": "Edward Walter Gillespie",
        "winner": "Democratic",
        "margin": 9802,
        "margin_pct": -20.729618272179337,
        "color": "#3182bd"
      },
      "16": {
        "dem_votes": 29670,
        "rep_votes": 32996,
        "other_votes": 2201,
        "total_votes": 64867,
        "dem_candidate": "Mark Robert Warner",
        "rep_candidate": "Edward Walter Gillespie",
        "winner": "Republican",
        "margin": 3326,
        "margin_pct": 5.127414555937534,
        "color": "#fcae91"
      },
      "17": {
        "dem_votes": 32282,
        "rep_votes": 26419,
        "other_votes": 1096,
        "total_votes": 59797,
        "dem_candidate": "Mark Robert Warner",
        "rep_candidate": "Edward Walter Gillespie",
        "winner": "Democratic",
        "margin": 5863,
        "margin_pct": -9.804839707677642,
        "color": "#9ecae1"
      },
      "18": {
        "dem_votes": 31946,
        "rep_votes": 18267,
        "other_votes": 1119,
        "total_votes": 51332,
        "dem_candidate": "Mark Robert Warner",
        "rep_candidate": "Edward Walter Gillespie",
        "winner": "Democratic",
        "margin": 13679,
        "margin_pct": -26.64809475570794,
        "color": "#3182bd"
      },
      "19": {
        "dem_votes": 20287,
        "rep_votes": 30183,
        "other_votes": 1295,
        "total_votes": 51765,
        "dem_candidate": "Mark Robert Warner",
        "rep_candidate": "Edward Walter Gillespie",
        "winner": "Republican",
        "margin": 9896,
        "margin_pct": 19.11716410702212,
        "color": "#ef3b2c"
      },
      "2": {
        "dem_votes": 14816,
        "rep_votes": 31959,
        "other_votes": 1433,
        "total_votes": 48208,
        "dem_candidate": "Mark Robert Warner",
        "rep_candidate": "Edward Walter Gillespie",
        "winner": "Republican",
        "margin": 17143,
        "margin_pct": 35.56048788582808,
        "color": "#a50f15"
      },
      "20": {
        "dem_votes": 24716,
        "rep_votes": 30561,
        "other_votes": 1606,
        "total_votes": 56883,
        "dem_candidate": "Mark Robert Warner",
        "rep_candidate": "Edward Walter Gillespie",
        "winner": "Republican",
        "margin": 5845,
        "margin_pct": 10.275477734999912,
        "color": "#ef3b2c"
      },
      "21": {
        "dem_votes": 26767,
        "rep_votes": 9848,
        "other_votes": 894,
        "total_votes": 37509,
        "dem_candidate": "Mark Robert Warner",
        "rep_candidate": "Edward Walter Gillespie",
        "winner": "Democratic",
        "margin": 16919,
        "margin_pct": -45.10650777146818,
        "color": "#08306b"
      },
      "22": {
        "dem_votes": 23313,
        "rep_votes": 19843,
        "other_votes": 1217,
        "total_votes": 44373,
        "dem_candidate": "Mark Robert Warner",
        "rep_candidate": "Edward Walter Gillespie",
        "winner": "Democratic",
        "margin": 3470,
        "margin_pct": -7.820070763752733,
        "color": "#9ecae1"
      },
      "23": {
        "dem_votes": 33503,
        "rep_votes": 14552,
        "other_votes": 952,
        "total_votes": 49007,
        "dem_candidate": "Mark Robert Warner",
        "rep_candidate": "Edward Walter Gillespie",
        "winner": "Democratic",
        "margin": 18951,
        "margin_pct": -38.66998592037872,
        "color": "#08519c"
      },
      "24": {
        "dem_votes": 25365,
        "rep_votes": 26975,
        "other_votes": 1284,
        "total_votes": 53624,
        "dem_candidate": "Mark Robert Warner",
        "rep_candidate": "Edward Walter Gillespie",
        "winner": "Republican",
        "margin": 1610,
        "margin_pct": 3.002386990899597,
        "color": "#fcae91"
      },
      "25": {
        "dem_votes": 24259,
        "rep_votes": 32209,
        "other_votes": 1371,
        "total_votes": 57839,
        "dem_candidate": "Mark Robert Warner",
        "rep_candidate": "Edward Walter Gillespie",
        "winner": "Republican",
        "margin": 7950,
        "margin_pct": 13.745050917201196,
        "color": "#ef3b2c"
      },
      "26": {
        "dem_votes": 26046,
        "rep_votes": 45303,
        "other_votes": 1885,
        "total_votes": 73234,
        "dem_candidate": "Mark Robert Warner",
        "rep_candidate": "Edward Walter Gillespie",
        "winner": "Republican",
        "margin": 19257,
        "margin_pct": 26.29516344867138,
        "color": "#cb181d"
      },
      "27": {
        "dem_votes": 19926,
        "rep_votes": 27451,
        "other_votes": 1130,
        "total_votes": 48507,
        "dem_candidate": "Mark Robert Warner",
        "rep_candidate": "Edward Walter Gillespie",
        "winner": "Republican",
        "margin": 7525,
        "margin_pct": 15.513224895375924,
        "color": "#ef3b2c"
      },
      "28": {
        "dem_votes": 18426,
        "rep_votes": 34058,
        "other_votes": 1388,
        "total_votes": 53872,
        "dem_candidate": "Mark Robert Warner",
        "rep_candidate": "Edward Walter Gillespie",
        "winner": "Republican",
        "margin": 15632,
        "margin_pct": 29.016929016929016,
        "color": "#cb181d"
      },
      "29": {
        "dem_votes": 21244,
        "rep_votes": 20458,
        "other_votes": 883,
        "total_votes": 42585,
        "dem_candidate": "Mark Robert Warner",
        "rep_candidate": "Edward Walter Gillespie",
        "winner": "Democratic",
        "margin": 786,
        "margin_pct": -1.8457203240577666,
        "color": "#c6dbef"
      },
      "3": {
        "dem_votes": 22981,
        "rep_votes": 34401,
        "other_votes": 1651,
        "total_votes": 59033,
        "dem_candidate": "Mark Robert Warner",
        "rep_candidate": "Edward Walter Gillespie",
        "winner": "Republican",
        "margin": 11420,
        "margin_pct": 19.3451120559687,
        "color": "#ef3b2c"
      },
      "30": {
        "dem_votes": 18481,
        "rep_votes": 21446,
        "other_votes": 1022,
        "total_votes": 40949,
        "dem_candidate": "Mark Robert Warner",
        "rep_candidate": "Edward Walter Gillespie",
        "winner": "Republican",
        "margin": 2965,
        "margin_pct": 7.240714058951378,
        "color": "#fb6a4a"
      },
      "31": {
        "dem_votes": 27817,
        "rep_votes": 31624,
        "other_votes": 1354,
        "total_votes": 60795,
        "dem_candidate": "Mark Robert Warner",
        "rep_candidate": "Edward Walter Gillespie",
        "winner": "Republican",
        "margin": 3807,
        "margin_pct": 6.262028127313101,
        "color": "#fb6a4a"
      },
      "32": {
        "dem_votes": 19732,
        "rep_votes": 18002,
        "other_votes": 919,
        "total_votes": 38653,
        "dem_candidate": "Mark Robert Warner",
        "rep_candidate": "Edward Walter Gillespie",
        "winner": "Democratic",
        "margin": 1730,
        "margin_pct": -4.475719866504541,
        "color": "#c6dbef"
      },
      "33": {
        "dem_votes": 28469,
        "rep_votes": 22727,
        "other_votes": 1052,
        "total_votes": 52248,
        "dem_candidate": "Mark Robert Warner",
        "rep_candidate": "Edward Walter Gillespie",
        "winner": "Democratic",
        "margin": 5742,
        "margin_pct": -10.989894350022968,
        "color": "#6baed6"
      },
      "34": {
        "dem_votes": 31998,
        "rep_votes": 19494,
        "other_votes": 1041,
        "total_votes": 52533,
        "dem_candidate": "Mark Robert Warner",
        "rep_candidate": "Edward Walter Gillespie",
        "winner": "Democratic",
        "margin": 12504,
        "margin_pct": -23.802181485923136,
        "color": "#3182bd"
      },
      "35": {
        "dem_votes": 34061,
        "rep_votes": 22684,
        "other_votes": 1296,
        "total_votes": 58041,
        "dem_candidate": "Mark Robert Warner",
        "rep_candidate": "Edward Walter Gillespie",
        "winner": "Democratic",
        "margin": 11377,
        "margin_pct": -19.601660894884652,
        "color": "#6baed6"
      },
      "36": {
        "dem_votes": 28683,
        "rep_votes": 25537,
        "other_votes": 1280,
        "total_votes": 55500,
        "dem_candidate": "Mark Robert Warner",
        "rep_candidate": "Edward Walter Gillespie",
        "winner": "Democratic",
        "margin": 3146,
        "margin_pct": -5.668468468468468,
        "color": "#9ecae1"
      },
      "37": {
        "dem_votes": 33799,
        "rep_votes": 20691,
        "other_votes": 1326,
        "total_votes": 55816,
        "dem_candidate": "Mark Robert Warner",
        "rep_candidate": "Edward Walter Gillespie",
        "winner": "Democratic",
        "margin": 13108,
        "margin_pct": -23.484305575462233,
        "color": "#3182bd"
      },
      "38": {
        "dem_votes": 37974,
        "rep_votes": 24857,
        "other_votes": 1292,
        "total_votes": 64123,
        "dem_candidate": "Mark Robert Warner",
        "rep_candidate": "Edward Walter Gillespie",
        "winner": "Democratic",
        "margin": 13117,
        "margin_pct": -20.45599862763751,
        "color": "#3182bd"
      },
      "39": {
        "dem_votes": 37088,
        "rep_votes": 15009,
        "other_votes": 1200,
        "total_votes": 53297,
        "dem_candidate": "Mark Robert Warner",
        "rep_candidate": "Edward Walter Gillespie",
        "winner": "Democratic",
        "margin": 22079,
        "margin_pct": -41.426346698688484,
        "color": "#08306b"
      },
      "4": {
        "dem_votes": 26762,
        "rep_votes": 26824,
        "other_votes": 1783,
        "total_votes": 55369,
        "dem_candidate": "Mark Robert Warner",
        "rep_candidate": "Edward Walter Gillespie",
        "winner": "Republican",
        "margin": 62,
        "margin_pct": 0.11197601545991438,
        "color": "#f7f7f7"
      },
      "40": {
        "dem_votes": 43672,
        "rep_votes": 16186,
        "other_votes": 1564,
        "total_votes": 61422,
        "dem_candidate": "Mark Robert Warner",
        "rep_candidate": "Edward Walter Gillespie",
        "winner": "Democratic",
        "margin": 27486,
        "margin_pct": -44.749438312005466,
        "color": "#08306b"
      },
      "5": {
        "dem_votes": 19491,
        "rep_votes": 28438,
        "other_votes": 1395,
        "total_votes": 49324,
        "dem_candidate": "Mark Robert Warner",
        "rep_candidate": "Edward Walter Gillespie",
        "winner": "Republican",
        "margin": 8947,
        "margin_pct": 18.13924255940313,
        "color": "#ef3b2c"
      },
      "6": {
        "dem_votes": 17259,
        "rep_votes": 33709,
        "other_votes": 862,
        "total_votes": 51830,
        "dem_candidate": "Mark Robert Warner",
        "rep_candidate": "Edward Walter Gillespie",
        "winner": "Republican",
        "margin": 16450,
        "margin_pct": 31.738375458228823,
        "color": "#a50f15"
      },
      "7": {
        "dem_votes": 22228,
        "rep_votes": 34563,
        "other_votes": 1480,
        "total_votes": 58271,
        "dem_candidate": "Mark Robert Warner",
        "rep_candidate": "Edward Walter Gillespie",
        "winner": "Republican",
        "margin": 12335,
        "margin_pct": 21.168334162791098,
        "color": "#cb181d"
      },
      "8": {
        "dem_votes": 19567,
        "rep_votes": 38668,
        "other_votes": 1366,
        "total_votes": 59601,
        "dem_candidate": "Mark Robert Warner",
        "rep_candidate": "Edward Walter Gillespie",
        "winner": "Republican",
        "margin": 19101,
        "margin_pct": 32.04811999798661,
        "color": "#a50f15"
      },
      "9": {
        "dem_votes": 26441,
        "rep_votes": 31945,
        "other_votes": 924,
        "total_votes": 59310,
        "dem_candidate": "Mark Robert Warner",
        "rep_candidate": "Edward Walter Gillespie",
        "winner": "Republican",
        "margin": 5504,
        "margin_pct": 9.280053953802057,
        "color": "#fb6a4a"
      }
    }
  }
}