{
  "meta": {
    "scope": "state_senate",
    "contest_type": "president",
    "year": 2020,
    "district_count": 40,
    "input_votes": 4460524,
    "matched_votes": 4460524,
    "direct_matched_votes": 1628647,
    "allocated_votes": 2831877,
    "match_coverage_pct": 100.0,
    "direct_match_coverage_pct": 36.51245907431503
  },
  "general": {
    "results": {
      "1": {
        "dem_votes": 41176,
        "rep_votes": 71503,
        "other_votes": 2298,
        "total_votes": 114977,
        "dem_candidate": "Joseph Robinette Biden, Jr",
        "rep_candidate": "Donald J. Trump",
        "winner": "Republican",
        "margin": 30327,
        "margin_pct": 26.376579663758836,
        "color": "#cb181d"
      },
      "10": {
        "dem_votes": 47962,
        "rep_votes": 80243,
        "other_votes": 2163,
        "total_votes": 130368,
        "dem_candidate": "Joseph Robinette Biden, Jr",
        "rep_candidate": "Donald J. Trump",
        "winner": "Republican",
        "margin": 32281,
        "margin_pct": 24.761444526264114,
        "color": "#cb181d"
      },
      "11": {
        "dem_votes": 75190,
        "rep_votes": 42591,
        "other_votes": 2357,
        "total_votes": 120138,
        "dem_candidate": "Joseph Robinette Biden, Jr",
        "rep_candidate": "Donald J. Trump",
        "winner": "Democratic",
        "margin": 32599,
        "margin_pct": -27.134628510546204,
        "color": "#3182bd"
      },
      "12": {
        "dem_votes": 58344,
        "rep_votes": 66041,
        "other_votes": 2471,
        "total_votes": 126856,
        "dem_candidate": "Joseph Robinette Biden, Jr",
        "rep_candidate": "Donald J. Trump",
        "winner": "Republican",
        "margin": 7697,
        "margin_pct": 6.067509617203759,
        "color": "#fb6a4a"
      },
      "13": {
        "dem_votes": 62622,
        "rep_votes": 39460,
        "other_votes": 1337,
        "total_votes": 103419,
        "dem_candidate": "Joseph Robinette Biden, Jr",
        "rep_candidate": "Donald J. Trump",
        "winner": "Democratic",
        "margin": 23162,
        "margin_pct": -22.39627147816165,
        "color": "#3182bd"
      },
      "14": {
        "dem_votes": 94030,
        "rep_votes": 20414,
        "other_votes": 2461,
        "total_votes": 116905,
        "dem_candidate": "Joseph Robinette Biden, Jr",
        "rep_candidate": "Donald J. Trump",
        "winner": "Democratic",
        "margin": 73616,
        "margin_pct": -62.970788246867116,
        "color": "#08306b"
      },
      "15": {
        "dem_votes": 68430,
        "rep_votes": 35763,
        "other_votes": 1660,
        "total_votes": 105853,
        "dem_candidate": "Joseph Robinette Biden, Jr",
        "rep_candidate": "Donald J. Trump",
        "winner": "Democratic",
        "margin": 32667,
        "margin_pct": -30.860721944583524,
        "color": "#08519c"
      },
      "16": {
        "dem_votes": 69092,
        "rep_votes": 48698,
        "other_votes": 2176,
        "total_votes": 119966,
        "dem_candidate": "Joseph Robinette Biden, Jr",
        "rep_candidate": "Donald J. Trump",
        "winner": "Democratic",
        "margin": 20394,
        "margin_pct": -16.9998166147075,
        "color": "#6baed6"
      },
      "17": {
        "dem_votes": 61086,
        "rep_votes": 52494,
        "other_votes": 1689,
        "total_votes": 115269,
        "dem_candidate": "Joseph Robinette Biden, Jr",
        "rep_candidate": "Donald J. Trump",
        "winner": "Democratic",
        "margin": 8592,
        "margin_pct": -7.453868776514066,
        "color": "#9ecae1"
      },
      "18": {
        "dem_votes": 61581,
        "rep_votes": 37645,
        "other_votes": 2033,
        "total_votes": 101259,
        "dem_candidate": "Joseph Robinette Biden, Jr",
        "rep_candidate": "Donald J. Trump",
        "winner": "Democratic",
        "margin": 23936,
        "margin_pct": -23.638392636703898,
        "color": "#3182bd"
      },
      "19": {
        "dem_votes": 54793,
        "rep_votes": 57891,
        "other_votes": 2314,
        "total_votes": 114998,
        "dem_candidate": "Joseph Robinette Biden, Jr",
        "rep_candidate": "Donald J. Trump",
        "winner": "Republican",
        "margin": 3098,
        "margin_pct": 2.693959894954695,
        "color": "#fcae91"
      },
      "2": {
        "dem_votes": 34359,
        "rep_votes": 67137,
        "other_votes": 1936,
        "total_votes": 103432,
        "dem_candidate": "Joseph Robinette Biden, Jr",
        "rep_candidate": "Donald J. Trump",
        "winner": "Republican",
        "margin": 32778,
        "margin_pct": 31.690385954056772,
        "color": "#a50f15"
      },
      "20": {
        "dem_votes": 52247,
        "rep_votes": 54425,
        "other_votes": 2241,
        "total_votes": 108913,
        "dem_candidate": "Joseph Robinette Biden, Jr",
        "rep_candidate": "Donald J. Trump",
        "winner": "Republican",
        "margin": 2178,
        "margin_pct": 1.9997612773498115,
        "color": "#fcae91"
      },
      "21": {
        "dem_votes": 56858,
        "rep_votes": 19069,
        "other_votes": 1708,
        "total_votes": 77635,
        "dem_candidate": "Joseph Robinette Biden, Jr",
        "rep_candidate": "Donald J. Trump",
        "winner": "Democratic",
        "margin": 37789,
        "margin_pct": -48.67521092290848,
        "color": "#08306b"
      },
      "22": {
        "dem_votes": 55834,
        "rep_votes": 42998,
        "other_votes": 2355,
        "total_votes": 101187,
        "dem_candidate": "Joseph Robinette Biden, Jr",
        "rep_candidate": "Donald J. Trump",
        "winner": "Democratic",
        "margin": 12836,
        "margin_pct": -12.68542401691917,
        "color": "#6baed6"
      },
      "23": {
        "dem_votes": 67057,
        "rep_votes": 26761,
        "other_votes": 1837,
        "total_votes": 95655,
        "dem_candidate": "Joseph Robinette Biden, Jr",
        "rep_candidate": "Donald J. Trump",
        "winner": "Democratic",
        "margin": 40296,
        "margin_pct": -42.12639172024463,
        "color": "#08306b"
      },
      "24": {
        "dem_votes": 57474,
        "rep_votes": 47788,
        "other_votes": 2366,
        "total_votes": 107628,
        "dem_candidate": "Joseph Robinette Biden, Jr",
        "rep_candidate": "Donald J. Trump",
        "winner": "Democratic",
        "margin": 9686,
        "margin_pct": -8.99951685435017,
        "color": "#9ecae1"
      },
      "25": {
        "dem_votes": 49665,
        "rep_votes": 64862,
        "other_votes": 2011,
        "total_votes": 116538,
        "dem_candidate": "Joseph Robinette Biden, Jr",
        "rep_candidate": "Donald J. Trump",
        "winner": "Republican",
        "margin": 15197,
        "margin_pct": 13.040381678079251,
        "color": "#ef3b2c"
      },
      "26": {
        "dem_votes": 53470,
        "rep_votes": 79304,
        "other_votes": 2515,
        "total_votes": 135289,
        "dem_candidate": "Joseph Robinette Biden, Jr",
        "rep_candidate": "Donald J. Trump",
        "winner": "Republican",
        "margin": 25834,
        "margin_pct": 19.09541795711403,
        "color": "#ef3b2c"
      },
      "27": {
        "dem_votes": 55789,
        "rep_votes": 50191,
        "other_votes": 2425,
        "total_votes": 108405,
        "dem_candidate": "Joseph Robinette Biden, Jr",
        "rep_candidate": "Donald J. Trump",
        "winner": "Democratic",
        "margin": 5598,
        "margin_pct": -5.163968451639684,
        "color": "#c6dbef"
      },
      "28": {
        "dem_votes": 46921,
        "rep_votes": 71128,
        "other_votes": 2320,
        "total_votes": 120369,
        "dem_candidate": "Joseph Robinette Biden, Jr",
        "rep_candidate": "Donald J. Trump",
        "winner": "Republican",
        "margin": 24207,
        "margin_pct": 20.11065972135683,
        "color": "#cb181d"
      },
      "29": {
        "dem_votes": 64498,
        "rep_votes": 39447,
        "other_votes": 1891,
        "total_votes": 105836,
        "dem_candidate": "Joseph Robinette Biden, Jr",
        "rep_candidate": "Donald J. Trump",
        "winner": "Democratic",
        "margin": 25051,
        "margin_pct": -23.66963982009902,
        "color": "#3182bd"
      },
      "3": {
        "dem_votes": 42288,
        "rep_votes": 75454,
        "other_votes": 2241,
        "total_votes": 119983,
        "dem_candidate": "Joseph Robinette Biden, Jr",
        "rep_candidate": "Donald J. Trump",
        "winner": "Republican",
        "margin": 33166,
        "margin_pct": 27.642249318653477,
        "color": "#cb181d"
      },
      "30": {
        "dem_votes": 55096,
        "rep_votes": 33900,
        "other_votes": 1693,
        "total_votes": 90689,
        "dem_candidate": "Joseph Robinette Biden, Jr",
        "rep_candidate": "Donald J. Trump",
        "winner": "Democratic",
        "margin": 21196,
        "margin_pct": -23.372184057603455,
        "color": "#3182bd"
      },
      "31": {
        "dem_votes": 77089,
        "rep_votes": 59020,
        "other_votes": 2877,
        "total_votes": 138986,
        "dem_candidate": "Joseph Robinette Biden, Jr",
        "rep_candidate": "Donald J. Trump",
        "winner": "Democratic",
        "margin": 18069,
        "margin_pct": -13.000589987480755,
        "color": "#6baed6"
      },
      "32": {
        "dem_votes": 63695,
        "rep_votes": 34426,
        "other_votes": 1852,
        "total_votes": 99973,
        "dem_candidate": "Joseph Robinette Biden, Jr",
        "rep_candidate": "Donald J. Trump",
        "winner": "Democratic",
        "margin": 29269,
        "margin_pct": -29.27690476428636,
        "color": "#3182bd"
      },
      "33": {
        "dem_votes": 79042,
        "rep_votes": 36602,
        "other_votes": 2165,
        "total_votes": 117809,
        "dem_candidate": "Joseph Robinette Biden, Jr",
        "rep_candidate": "Donald J. Trump",
        "winner": "Democratic",
        "margin": 42440,
        "margin_pct": -36.024412396336444,
        "color": "#08519c"
      },
      "34": {
        "dem_votes": 84104,
        "rep_votes": 30766,
        "other_votes": 2346,
        "total_votes": 117216,
        "dem_candidate": "Joseph Robinette Biden, Jr",
        "rep_candidate": "Donald J. Trump",
        "winner": "Democratic",
        "margin": 53338,
        "margin_pct": -45.504026754026754,
        "color": "#08306b"
      },
      "35": {
        "dem_votes": 89584,
        "rep_votes": 34894,
        "other_votes": 2515,
        "total_votes": 126993,
        "dem_candidate": "Joseph Robinette Biden, Jr",
        "rep_candidate": "Donald J. Trump",
        "winner": "Democratic",
        "margin": 54690,
        "margin_pct": -43.0653658075642,
        "color": "#08306b"
      },
      "36": {
        "dem_votes": 75559,
        "rep_votes": 33244,
        "other_votes": 2277,
        "total_votes": 111080,
        "dem_candidate": "Joseph Robinette Biden, Jr",
        "rep_candidate": "Donald J. Trump",
        "winner": "Democratic",
        "margin": 42315,
        "margin_pct": -38.09416636658264,
        "color": "#08519c"
      },
      "37": {
        "dem_votes": 68733,
        "rep_votes": 26795,
        "other_votes": 2160,
        "total_votes": 97688,
        "dem_candidate": "Joseph Robinette Biden, Jr",
        "rep_candidate": "Donald J. Trump",
        "winner": "Democratic",
        "margin": 41938,
        "margin_pct": -42.93055441814757,
        "color": "#08306b"
      },
      "38": {
        "dem_votes": 72526,
        "rep_votes": 29688,
        "other_votes": 2360,
        "total_votes": 104574,
        "dem_candidate": "Joseph Robinette Biden, Jr",
        "rep_candidate": "Donald J. Trump",
        "winner": "Democratic",
        "margin": 42838,
        "margin_pct": -40.96429322776216,
        "color": "#08306b"
      },
      "39": {
        "dem_votes": 86759,
        "rep_votes": 19708,
        "other_votes": 2251,
        "total_votes": 108718,
        "dem_candidate": "Joseph Robinette Biden, Jr",
        "rep_candidate": "Donald J. Trump",
        "winner": "Democratic",
        "margin": 67051,
        "margin_pct": -61.674239776301995,
        "color": "#08306b"
      },
      "4": {
        "dem_votes": 53039,
        "rep_votes": 51471,
        "other_votes": 2299,
        "total_votes": 106809,
        "dem_candidate": "Joseph Robinette Biden, Jr",
        "rep_candidate": "Donald J. Trump",
        "winner": "Democratic",
        "margin": 1568,
        "margin_pct": -1.4680410826802985,
        "color": "#c6dbef"
      },
      "40": {
        "dem_votes": 94861,
        "rep_votes": 20075,
        "other_votes": 2729,
        "total_votes": 117665,
        "dem_candidate": "Joseph Robinette Biden, Jr",
        "rep_candidate": "Donald J. Trump",
        "winner": "Democratic",
        "margin": 74786,
        "margin_pct": -63.55840734288021,
        "color": "#08306b"
      },
      "5": {
        "dem_votes": 32596,
        "rep_votes": 67264,
        "other_votes": 1793,
        "total_votes": 101653,
        "dem_candidate": "Joseph Robinette Biden, Jr",
        "rep_candidate": "Donald J. Trump",
        "winner": "Republican",
        "margin": 34668,
        "margin_pct": 34.10425663777754,
        "color": "#a50f15"
      },
      "6": {
        "dem_votes": 21148,
        "rep_votes": 83867,
        "other_votes": 1149,
        "total_votes": 106164,
        "dem_candidate": "Joseph Robinette Biden, Jr",
        "rep_candidate": "Donald J. Trump",
        "winner": "Republican",
        "margin": 62719,
        "margin_pct": 59.07746505406729,
        "color": "#67000d"
      },
      "7": {
        "dem_votes": 33085,
        "rep_votes": 81559,
        "other_votes": 1385,
        "total_votes": 116029,
        "dem_candidate": "Joseph Robinette Biden, Jr",
        "rep_candidate": "Donald J. Trump",
        "winner": "Republican",
        "margin": 48474,
        "margin_pct": 41.777486662817054,
        "color": "#67000d"
      },
      "8": {
        "dem_votes": 38294,
        "rep_votes": 73942,
        "other_votes": 2688,
        "total_votes": 114924,
        "dem_candidate": "Joseph Robinette Biden, Jr",
        "rep_candidate": "Donald J. Trump",
        "winner": "Republican",
        "margin": 35648,
        "margin_pct": 31.018760224148135,
        "color": "#a50f15"
      },
      "9": {
        "dem_votes": 46691,
        "rep_votes": 64796,
        "other_votes": 1183,
        "total_votes": 112670,
        "dem_candidate": "Joseph Robinette Biden, Jr",
        "rep_candidate": "Donald J. Trump",
        "winner": "Republican",
        "margin": 18105,
        "margin_pct": 16.069051211502618,
        "color": "#ef3b2c"
      }
    }
  }
}