{
  "meta": {
    "scope": "state_senate",
    "contest_type": "us_senate",
    "year": 2018,
    "district_count": 40,
    "input_votes": 3351757,
    "matched_votes": 3351757,
    "direct_matched_votes": 3015866,
    "allocated_votes": 335891,
    "match_coverage_pct": 100.0,
    "direct_match_coverage_pct": 89.97865895409483
  },
  "general": {
    "results": {
      "1": {
        "dem_votes": 31759,
        "rep_votes": 47853,
        "other_votes": 1662,
        "total_votes": 81274,
        "dem_candidate": "Timothy Michael Kaine",
        "rep_candidate": "Corey Alan Stewart",
        "winner": "Republican",
        "margin": 16094,
        "margin_pct": 19.802150749317125,
        "color": "#ef3b2c"
      },
      "10": {
        "dem_votes": 38030,
        "rep_votes": 55922,
        "other_votes": 1847,
        "total_votes": 95799,
        "dem_candidate": "Timothy Michael Kaine",
        "rep_candidate": "Corey Alan Stewart",
        "winner": "Republican",
        "margin": 17892,
        "margin_pct": 18.676604139917956,
        "color": "#ef3b2c"
      },
      "11": {
        "dem_votes": 64046,
        "rep_votes": 32136,
        "other_votes": 2213,
        "total_votes": 98395,
        "dem_candidate": "Timothy Michael Kaine",
        "rep_candidate": "Corey Alan Stewart",
        "winner": "Democratic",
        "margin": 31910,
        "margin_pct": -32.43050968036994,
        "color": "#08519c"
      },
      "12": {
        "dem_votes": 50091,
        "rep_votes": 50205,
        "other_votes": 2170,
        "total_votes": 102466,
        "dem_candidate": "Timothy Michael Kaine",
        "rep_candidate": "Corey Alan Stewart",
        "winner": "Republican",
        "margin": 114,
        "margin_pct": 0.11125641676263345,
        "color": "#f7f7f7"
      },
      "13": {
        "dem_votes": 51652,
        "rep_votes": 26832,
        "other_votes": 891,
        "total_votes": 79375,
        "dem_candidate": "Timothy Michael Kaine",
        "rep_candidate": "Corey Alan Stewart",
        "winner": "Democratic",
        "margin": 24820,
        "margin_pct": -31.26929133858268,
        "color": "#08519c"
      },
      "14": {
        "dem_votes": 74628,
        "rep_votes": 13445,
        "other_votes": 1863,
        "total_votes": 89936,
        "dem_candidate": "Timothy Michael Kaine",
        "rep_candidate": "Corey Alan Stewart",
        "winner": "Democratic",
        "margin": 61183,
        "margin_pct": -68.02948763565202,
        "color": "#08306b"
      },
      "15": {
        "dem_votes": 48661,
        "rep_votes": 23201,
        "other_votes": 1073,
        "total_votes": 72935,
        "dem_candidate": "Timothy Michael Kaine",
        "rep_candidate": "Corey Alan Stewart",
        "winner": "Democratic",
        "margin": 25460,
        "margin_pct": -34.907794611640504,
        "color": "#08519c"
      },
      "16": {
        "dem_votes": 59431,
        "rep_votes": 36832,
        "other_votes": 2348,
        "total_votes": 98611,
        "dem_candidate": "Timothy Michael Kaine",
        "rep_candidate": "Corey Alan Stewart",
        "winner": "Democratic",
        "margin": 22599,
        "margin_pct": -22.91732159698208,
        "color": "#3182bd"
      },
      "17": {
        "dem_votes": 47487,
        "rep_votes": 35761,
        "other_votes": 1122,
        "total_votes": 84370,
        "dem_candidate": "Timothy Michael Kaine",
        "rep_candidate": "Corey Alan Stewart",
        "winner": "Democratic",
        "margin": 11726,
        "margin_pct": -13.898305084745763,
        "color": "#6baed6"
      },
      "18": {
        "dem_votes": 49599,
        "rep_votes": 23879,
        "other_votes": 1261,
        "total_votes": 74739,
        "dem_candidate": "Timothy Michael Kaine",
        "rep_candidate": "Corey Alan Stewart",
        "winner": "Democratic",
        "margin": 25720,
        "margin_pct": -34.413090889629245,
        "color": "#08519c"
      },
      "19": {
        "dem_votes": 35585,
        "rep_votes": 41623,
        "other_votes": 1689,
        "total_votes": 78897,
        "dem_candidate": "Timothy Michael Kaine",
        "rep_candidate": "Corey Alan Stewart",
        "winner": "Republican",
        "margin": 6038,
        "margin_pct": 7.653015957514227,
        "color": "#fb6a4a"
      },
      "2": {
        "dem_votes": 26907,
        "rep_votes": 44891,
        "other_votes": 1594,
        "total_votes": 73392,
        "dem_candidate": "Timothy Michael Kaine",
        "rep_candidate": "Corey Alan Stewart",
        "winner": "Republican",
        "margin": 17984,
        "margin_pct": 24.50403313712666,
        "color": "#cb181d"
      },
      "20": {
        "dem_votes": 42408,
        "rep_votes": 39411,
        "other_votes": 1897,
        "total_votes": 83716,
        "dem_candidate": "Timothy Michael Kaine",
        "rep_candidate": "Corey Alan Stewart",
        "winner": "Democratic",
        "margin": 2997,
        "margin_pct": -3.5799608199149504,
        "color": "#c6dbef"
      },
      "21": {
        "dem_votes": 46326,
        "rep_votes": 12246,
        "other_votes": 1124,
        "total_votes": 59696,
        "dem_candidate": "Timothy Michael Kaine",
        "rep_candidate": "Corey Alan Stewart",
        "winner": "Democratic",
        "margin": 34080,
        "margin_pct": -57.08925221120344,
        "color": "#08306b"
      },
      "22": {
        "dem_votes": 44879,
        "rep_votes": 27046,
        "other_votes": 1692,
        "total_votes": 73617,
        "dem_candidate": "Timothy Michael Kaine",
        "rep_candidate": "Corey Alan Stewart",
        "winner": "Democratic",
        "margin": 17833,
        "margin_pct": -24.224024342203567,
        "color": "#3182bd"
      },
      "23": {
        "dem_votes": 53775,
        "rep_votes": 18338,
        "other_votes": 1055,
        "total_votes": 73168,
        "dem_candidate": "Timothy Michael Kaine",
        "rep_candidate": "Corey Alan Stewart",
        "winner": "Democratic",
        "margin": 35437,
        "margin_pct": -48.432374808659524,
        "color": "#08306b"
      },
      "24": {
        "dem_votes": 43475,
        "rep_votes": 32987,
        "other_votes": 1574,
        "total_votes": 78036,
        "dem_candidate": "Timothy Michael Kaine",
        "rep_candidate": "Corey Alan Stewart",
        "winner": "Democratic",
        "margin": 10488,
        "margin_pct": -13.439950791942183,
        "color": "#6baed6"
      },
      "25": {
        "dem_votes": 38839,
        "rep_votes": 43884,
        "other_votes": 1389,
        "total_votes": 84112,
        "dem_candidate": "Timothy Michael Kaine",
        "rep_candidate": "Corey Alan Stewart",
        "winner": "Republican",
        "margin": 5045,
        "margin_pct": 5.997955107475747,
        "color": "#fb6a4a"
      },
      "26": {
        "dem_votes": 42953,
        "rep_votes": 59403,
        "other_votes": 2021,
        "total_votes": 104377,
        "dem_candidate": "Timothy Michael Kaine",
        "rep_candidate": "Corey Alan Stewart",
        "winner": "Republican",
        "margin": 16450,
        "margin_pct": 15.760177050499632,
        "color": "#ef3b2c"
      },
      "27": {
        "dem_votes": 40977,
        "rep_votes": 35691,
        "other_votes": 1619,
        "total_votes": 78287,
        "dem_candidate": "Timothy Michael Kaine",
        "rep_candidate": "Corey Alan Stewart",
        "winner": "Democratic",
        "margin": 5286,
        "margin_pct": -6.752078889215323,
        "color": "#9ecae1"
      },
      "28": {
        "dem_votes": 35434,
        "rep_votes": 49996,
        "other_votes": 1660,
        "total_votes": 87090,
        "dem_candidate": "Timothy Michael Kaine",
        "rep_candidate": "Corey Alan Stewart",
        "winner": "Republican",
        "margin": 14562,
        "margin_pct": 16.72063382707544,
        "color": "#ef3b2c"
      },
      "29": {
        "dem_votes": 45382,
        "rep_votes": 24075,
        "other_votes": 1437,
        "total_votes": 70894,
        "dem_candidate": "Timothy Michael Kaine",
        "rep_candidate": "Corey Alan Stewart",
        "winner": "Democratic",
        "margin": 21307,
        "margin_pct": -30.054729596298703,
        "color": "#08519c"
      },
      "3": {
        "dem_votes": 32755,
        "rep_votes": 49472,
        "other_votes": 1581,
        "total_votes": 83808,
        "dem_candidate": "Timothy Michael Kaine",
        "rep_candidate": "Corey Alan Stewart",
        "winner": "Republican",
        "margin": 16717,
        "margin_pct": 19.946783123329514,
        "color": "#ef3b2c"
      },
      "30": {
        "dem_votes": 42872,
        "rep_votes": 27209,
        "other_votes": 1685,
        "total_votes": 71766,
        "dem_candidate": "Timothy Michael Kaine",
        "rep_candidate": "Corey Alan Stewart",
        "winner": "Democratic",
        "margin": 15663,
        "margin_pct": -21.825098235933453,
        "color": "#3182bd"
      },
      "31": {
        "dem_votes": 53662,
        "rep_votes": 37773,
        "other_votes": 2125,
        "total_votes": 93560,
        "dem_candidate": "Timothy Michael Kaine",
        "rep_candidate": "Corey Alan Stewart",
        "winner": "Democratic",
        "margin": 15889,
        "margin_pct": -16.982684908080376,
        "color": "#6baed6"
      },
      "32": {
        "dem_votes": 56164,
        "rep_votes": 24872,
        "other_votes": 1638,
        "total_votes": 82674,
        "dem_candidate": "Timothy Michael Kaine",
        "rep_candidate": "Corey Alan Stewart",
        "winner": "Democratic",
        "margin": 31292,
        "margin_pct": -37.849868156857056,
        "color": "#08519c"
      },
      "33": {
        "dem_votes": 57534,
        "rep_votes": 23799,
        "other_votes": 1660,
        "total_votes": 82993,
        "dem_candidate": "Timothy Michael Kaine",
        "rep_candidate": "Corey Alan Stewart",
        "winner": "Democratic",
        "margin": 33735,
        "margin_pct": -40.64800645837601,
        "color": "#08306b"
      },
      "34": {
        "dem_votes": 63415,
        "rep_votes": 20608,
        "other_votes": 1992,
        "total_votes": 86015,
        "dem_candidate": "Timothy Michael Kaine",
        "rep_candidate": "Corey Alan Stewart",
        "winner": "Democratic",
        "margin": 42807,
        "margin_pct": -49.76690112189735,
        "color": "#08306b"
      },
      "35": {
        "dem_votes": 67612,
        "rep_votes": 24860,
        "other_votes": 2072,
        "total_votes": 94544,
        "dem_candidate": "Timothy Michael Kaine",
        "rep_candidate": "Corey Alan Stewart",
        "winner": "Democratic",
        "margin": 42752,
        "margin_pct": -45.21915721780335,
        "color": "#08306b"
      },
      "36": {
        "dem_votes": 60433,
        "rep_votes": 27540,
        "other_votes": 1832,
        "total_votes": 89805,
        "dem_candidate": "Timothy Michael Kaine",
        "rep_candidate": "Corey Alan Stewart",
        "winner": "Democratic",
        "margin": 32893,
        "margin_pct": -36.62713657368744,
        "color": "#08519c"
      },
      "37": {
        "dem_votes": 64415,
        "rep_votes": 21317,
        "other_votes": 2119,
        "total_votes": 87851,
        "dem_candidate": "Timothy Michael Kaine",
        "rep_candidate": "Corey Alan Stewart",
        "winner": "Democratic",
        "margin": 43098,
        "margin_pct": -49.05806422237652,
        "color": "#08306b"
      },
      "38": {
        "dem_votes": 66188,
        "rep_votes": 25118,
        "other_votes": 2110,
        "total_votes": 93416,
        "dem_candidate": "Timothy Michael Kaine",
        "rep_candidate": "Corey Alan Stewart",
        "winner": "Democratic",
        "margin": 41070,
        "margin_pct": -43.96463132653935,
        "color": "#08306b"
      },
      "39": {
        "dem_votes": 70624,
        "rep_votes": 14447,
        "other_votes": 2316,
        "total_votes": 87387,
        "dem_candidate": "Timothy Michael Kaine",
        "rep_candidate": "Corey Alan Stewart",
        "winner": "Democratic",
        "margin": 56177,
        "margin_pct": -64.28530559465366,
        "color": "#08306b"
      },
      "4": {
        "dem_votes": 41302,
        "rep_votes": 38495,
        "other_votes": 1639,
        "total_votes": 81436,
        "dem_candidate": "Timothy Michael Kaine",
        "rep_candidate": "Corey Alan Stewart",
        "winner": "Democratic",
        "margin": 2807,
        "margin_pct": -3.4468785303796845,
        "color": "#c6dbef"
      },
      "40": {
        "dem_votes": 77441,
        "rep_votes": 14344,
        "other_votes": 2772,
        "total_votes": 94557,
        "dem_candidate": "Timothy Michael Kaine",
        "rep_candidate": "Corey Alan Stewart",
        "winner": "Democratic",
        "margin": 63097,
        "margin_pct": -66.7290628932813,
        "color": "#08306b"
      },
      "5": {
        "dem_votes": 30924,
        "rep_votes": 44213,
        "other_votes": 1489,
        "total_votes": 76626,
        "dem_candidate": "Timothy Michael Kaine",
        "rep_candidate": "Corey Alan Stewart",
        "winner": "Republican",
        "margin": 13289,
        "margin_pct": 17.3426774201968,
        "color": "#ef3b2c"
      },
      "6": {
        "dem_votes": 19941,
        "rep_votes": 50760,
        "other_votes": 784,
        "total_votes": 71485,
        "dem_candidate": "Timothy Michael Kaine",
        "rep_candidate": "Corey Alan Stewart",
        "winner": "Republican",
        "margin": 30819,
        "margin_pct": 43.112541092536894,
        "color": "#67000d"
      },
      "7": {
        "dem_votes": 26656,
        "rep_votes": 54663,
        "other_votes": 1042,
        "total_votes": 82361,
        "dem_candidate": "Timothy Michael Kaine",
        "rep_candidate": "Corey Alan Stewart",
        "winner": "Republican",
        "margin": 28007,
        "margin_pct": 34.00517235099137,
        "color": "#a50f15"
      },
      "8": {
        "dem_votes": 29519,
        "rep_votes": 52778,
        "other_votes": 2075,
        "total_votes": 84372,
        "dem_candidate": "Timothy Michael Kaine",
        "rep_candidate": "Corey Alan Stewart",
        "winner": "Republican",
        "margin": 23259,
        "margin_pct": 27.567202389418288,
        "color": "#cb181d"
      },
      "9": {
        "dem_votes": 36591,
        "rep_votes": 46383,
        "other_votes": 938,
        "total_votes": 83912,
        "dem_candidate": "Timothy Michael Kaine",
        "rep_candidate": "Corey Alan Stewart",
        "winner": "Republican",
        "margin": 9792,
        "margin_pct": 11.66936790923825,
        "color": "#ef3b2c"
      }
    }
  }
}