{
  "meta": {
    "scope": "state_senate",
    "contest_type": "us_senate",
    "year": 2008,
    "district_count": 40,
    "input_votes": 3159990,
    "matched_votes": 2926647,
    "match_coverage_pct": 92.61570448007747
  },
  "general": {
    "results": {
      "1": {
        "dem_votes": 47523,
        "rep_votes": 20859,
        "other_votes": 1021,
        "total_votes": 69403,
        "dem_candidate": "Mark R. Warner",
        "rep_candidate": "James Jim S. Gilmore, III",
        "winner": "Democratic",
        "margin": 26664,
        "margin_pct": -38.419088512023976,
        "color": "#08519c"
      },
      "10": {
        "dem_votes": 56373,
        "rep_votes": 30292,
        "other_votes": 1229,
        "total_votes": 87894,
        "dem_candidate": "Mark R. Warner",
        "rep_candidate": "James Jim S. Gilmore, III",
        "winner": "Democratic",
        "margin": 26081,
        "margin_pct": -29.673242769699865,
        "color": "#3182bd"
      },
      "11": {
        "dem_votes": 49165,
        "rep_votes": 38591,
        "other_votes": 1097,
        "total_votes": 88853,
        "dem_candidate": "Mark R. Warner",
        "rep_candidate": "James Jim S. Gilmore, III",
        "winner": "Democratic",
        "margin": 10574,
        "margin_pct": -11.900554849020292,
        "color": "#6baed6"
      },
      "12": {
        "dem_votes": 49818,
        "rep_votes": 34121,
        "other_votes": 980,
        "total_votes": 84919,
        "dem_candidate": "Mark R. Warner",
        "rep_candidate": "James Jim S. Gilmore, III",
        "winner": "Democratic",
        "margin": 15697,
        "margin_pct": -18.484673630165215,
        "color": "#6baed6"
      },
      "13": {
        "dem_votes": 35620,
        "rep_votes": 24672,
        "other_votes": 711,
        "total_votes": 61003,
        "dem_candidate": "Mark R. Warner",
        "rep_candidate": "James Jim S. Gilmore, III",
        "winner": "Democratic",
        "margin": 10948,
        "margin_pct": -17.94665836106421,
        "color": "#6baed6"
      },
      "14": {
        "dem_votes": 47746,
        "rep_votes": 37250,
        "other_votes": 854,
        "total_votes": 85850,
        "dem_candidate": "Mark R. Warner",
        "rep_candidate": "James Jim S. Gilmore, III",
        "winner": "Democratic",
        "margin": 10496,
        "margin_pct": -12.225975538730344,
        "color": "#6baed6"
      },
      "15": {
        "dem_votes": 45728,
        "rep_votes": 32417,
        "other_votes": 1094,
        "total_votes": 79239,
        "dem_candidate": "Mark R. Warner",
        "rep_candidate": "James Jim S. Gilmore, III",
        "winner": "Democratic",
        "margin": 13311,
        "margin_pct": -16.79854617044637,
        "color": "#6baed6"
      },
      "16": {
        "dem_votes": 54213,
        "rep_votes": 15589,
        "other_votes": 1096,
        "total_votes": 70898,
        "dem_candidate": "Mark R. Warner",
        "rep_candidate": "James Jim S. Gilmore, III",
        "winner": "Democratic",
        "margin": 38624,
        "margin_pct": -54.4782645490705,
        "color": "#08306b"
      },
      "17": {
        "dem_votes": 47479,
        "rep_votes": 26725,
        "other_votes": 890,
        "total_votes": 75094,
        "dem_candidate": "Mark R. Warner",
        "rep_candidate": "James Jim S. Gilmore, III",
        "winner": "Democratic",
        "margin": 20754,
        "margin_pct": -27.637361173995263,
        "color": "#3182bd"
      },
      "18": {
        "dem_votes": 54868,
        "rep_votes": 18241,
        "other_votes": 902,
        "total_votes": 74011,
        "dem_candidate": "Mark R. Warner",
        "rep_candidate": "James Jim S. Gilmore, III",
        "winner": "Democratic",
        "margin": 36627,
        "margin_pct": -49.48858953398819,
        "color": "#08306b"
      },
      "19": {
        "dem_votes": 52420,
        "rep_votes": 34662,
        "other_votes": 946,
        "total_votes": 88028,
        "dem_candidate": "Mark R. Warner",
        "rep_candidate": "James Jim S. Gilmore, III",
        "winner": "Democratic",
        "margin": 17758,
        "margin_pct": -20.173126732403325,
        "color": "#3182bd"
      },
      "2": {
        "dem_votes": 58886,
        "rep_votes": 15441,
        "other_votes": 1022,
        "total_votes": 75349,
        "dem_candidate": "Mark R. Warner",
        "rep_candidate": "James Jim S. Gilmore, III",
        "winner": "Democratic",
        "margin": 43445,
        "margin_pct": -57.658363083783456,
        "color": "#08306b"
      },
      "20": {
        "dem_votes": 53019,
        "rep_votes": 22190,
        "other_votes": 920,
        "total_votes": 76129,
        "dem_candidate": "Mark R. Warner",
        "rep_candidate": "James Jim S. Gilmore, III",
        "winner": "Democratic",
        "margin": 30829,
        "margin_pct": -40.495737498193854,
        "color": "#08306b"
      },
      "21": {
        "dem_votes": 40956,
        "rep_votes": 15874,
        "other_votes": 836,
        "total_votes": 57666,
        "dem_candidate": "Mark R. Warner",
        "rep_candidate": "James Jim S. Gilmore, III",
        "winner": "Democratic",
        "margin": 25082,
        "margin_pct": -43.495300523705474,
        "color": "#08306b"
      },
      "22": {
        "dem_votes": 46414,
        "rep_votes": 28518,
        "other_votes": 962,
        "total_votes": 75894,
        "dem_candidate": "Mark R. Warner",
        "rep_candidate": "James Jim S. Gilmore, III",
        "winner": "Democratic",
        "margin": 17896,
        "margin_pct": -23.580256673781854,
        "color": "#3182bd"
      },
      "23": {
        "dem_votes": 42123,
        "rep_votes": 39891,
        "other_votes": 862,
        "total_votes": 82876,
        "dem_candidate": "Mark R. Warner",
        "rep_candidate": "James Jim S. Gilmore, III",
        "winner": "Democratic",
        "margin": 2232,
        "margin_pct": -2.693180172788262,
        "color": "#c6dbef"
      },
      "24": {
        "dem_votes": 42400,
        "rep_votes": 38774,
        "other_votes": 1031,
        "total_votes": 82205,
        "dem_candidate": "Mark R. Warner",
        "rep_candidate": "James Jim S. Gilmore, III",
        "winner": "Democratic",
        "margin": 3626,
        "margin_pct": -4.41092390973785,
        "color": "#c6dbef"
      },
      "25": {
        "dem_votes": 49964,
        "rep_votes": 20438,
        "other_votes": 848,
        "total_votes": 71250,
        "dem_candidate": "Mark R. Warner",
        "rep_candidate": "James Jim S. Gilmore, III",
        "winner": "Democratic",
        "margin": 29526,
        "margin_pct": -41.44,
        "color": "#08306b"
      },
      "26": {
        "dem_votes": 38015,
        "rep_votes": 29587,
        "other_votes": 836,
        "total_votes": 68438,
        "dem_candidate": "Mark R. Warner",
        "rep_candidate": "James Jim S. Gilmore, III",
        "winner": "Democratic",
        "margin": 8428,
        "margin_pct": -12.314795873637454,
        "color": "#6baed6"
      },
      "27": {
        "dem_votes": 46632,
        "rep_votes": 35230,
        "other_votes": 890,
        "total_votes": 82752,
        "dem_candidate": "Mark R. Warner",
        "rep_candidate": "James Jim S. Gilmore, III",
        "winner": "Democratic",
        "margin": 11402,
        "margin_pct": -13.778518948182523,
        "color": "#6baed6"
      },
      "28": {
        "dem_votes": 46229,
        "rep_votes": 33454,
        "other_votes": 954,
        "total_votes": 80637,
        "dem_candidate": "Mark R. Warner",
        "rep_candidate": "James Jim S. Gilmore, III",
        "winner": "Democratic",
        "margin": 12775,
        "margin_pct": -15.84260327145107,
        "color": "#6baed6"
      },
      "29": {
        "dem_votes": 35317,
        "rep_votes": 16627,
        "other_votes": 652,
        "total_votes": 52596,
        "dem_candidate": "Mark R. Warner",
        "rep_candidate": "James Jim S. Gilmore, III",
        "winner": "Democratic",
        "margin": 18690,
        "margin_pct": -35.535021674652064,
        "color": "#08519c"
      },
      "3": {
        "dem_votes": 38213,
        "rep_votes": 32679,
        "other_votes": 922,
        "total_votes": 71814,
        "dem_candidate": "Mark R. Warner",
        "rep_candidate": "James Jim S. Gilmore, III",
        "winner": "Democratic",
        "margin": 5534,
        "margin_pct": -7.7060183251176655,
        "color": "#9ecae1"
      },
      "30": {
        "dem_votes": 56011,
        "rep_votes": 20426,
        "other_votes": 1196,
        "total_votes": 77633,
        "dem_candidate": "Mark R. Warner",
        "rep_candidate": "James Jim S. Gilmore, III",
        "winner": "Democratic",
        "margin": 35585,
        "margin_pct": -45.837466026045625,
        "color": "#08306b"
      },
      "31": {
        "dem_votes": 46678,
        "rep_votes": 20174,
        "other_votes": 983,
        "total_votes": 67835,
        "dem_candidate": "Mark R. Warner",
        "rep_candidate": "James Jim S. Gilmore, III",
        "winner": "Democratic",
        "margin": 26504,
        "margin_pct": -39.07127589002727,
        "color": "#08519c"
      },
      "32": {
        "dem_votes": 56285,
        "rep_votes": 25477,
        "other_votes": 1028,
        "total_votes": 82790,
        "dem_candidate": "Mark R. Warner",
        "rep_candidate": "James Jim S. Gilmore, III",
        "winner": "Democratic",
        "margin": 30808,
        "margin_pct": -37.212223698514315,
        "color": "#08519c"
      },
      "33": {
        "dem_votes": 30569,
        "rep_votes": 14893,
        "other_votes": 649,
        "total_votes": 46111,
        "dem_candidate": "Mark R. Warner",
        "rep_candidate": "James Jim S. Gilmore, III",
        "winner": "Democratic",
        "margin": 15676,
        "margin_pct": -33.99622649693132,
        "color": "#08519c"
      },
      "34": {
        "dem_votes": 50152,
        "rep_votes": 26155,
        "other_votes": 1006,
        "total_votes": 77313,
        "dem_candidate": "Mark R. Warner",
        "rep_candidate": "James Jim S. Gilmore, III",
        "winner": "Democratic",
        "margin": 23997,
        "margin_pct": -31.03876450273563,
        "color": "#08519c"
      },
      "35": {
        "dem_votes": 39169,
        "rep_votes": 14449,
        "other_votes": 783,
        "total_votes": 54401,
        "dem_candidate": "Mark R. Warner",
        "rep_candidate": "James Jim S. Gilmore, III",
        "winner": "Democratic",
        "margin": 24720,
        "margin_pct": -45.440341170199076,
        "color": "#08306b"
      },
      "36": {
        "dem_votes": 43710,
        "rep_votes": 17861,
        "other_votes": 765,
        "total_votes": 62336,
        "dem_candidate": "Mark R. Warner",
        "rep_candidate": "James Jim S. Gilmore, III",
        "winner": "Democratic",
        "margin": 25849,
        "margin_pct": -41.46720995893224,
        "color": "#08306b"
      },
      "37": {
        "dem_votes": 45216,
        "rep_votes": 23305,
        "other_votes": 925,
        "total_votes": 69446,
        "dem_candidate": "Mark R. Warner",
        "rep_candidate": "James Jim S. Gilmore, III",
        "winner": "Democratic",
        "margin": 21911,
        "margin_pct": -31.5511332546151,
        "color": "#08519c"
      },
      "38": {
        "dem_votes": 41305,
        "rep_votes": 22367,
        "other_votes": 661,
        "total_votes": 64333,
        "dem_candidate": "Mark R. Warner",
        "rep_candidate": "James Jim S. Gilmore, III",
        "winner": "Democratic",
        "margin": 18938,
        "margin_pct": -29.437458225172154,
        "color": "#3182bd"
      },
      "39": {
        "dem_votes": 47095,
        "rep_votes": 21657,
        "other_votes": 808,
        "total_votes": 69560,
        "dem_candidate": "Mark R. Warner",
        "rep_candidate": "James Jim S. Gilmore, III",
        "winner": "Democratic",
        "margin": 25438,
        "margin_pct": -36.56986774008051,
        "color": "#08519c"
      },
      "4": {
        "dem_votes": 49694,
        "rep_votes": 36345,
        "other_votes": 1063,
        "total_votes": 87102,
        "dem_candidate": "Mark R. Warner",
        "rep_candidate": "James Jim S. Gilmore, III",
        "winner": "Democratic",
        "margin": 13349,
        "margin_pct": -15.325710087024408,
        "color": "#6baed6"
      },
      "40": {
        "dem_votes": 38448,
        "rep_votes": 28341,
        "other_votes": 711,
        "total_votes": 67500,
        "dem_candidate": "Mark R. Warner",
        "rep_candidate": "James Jim S. Gilmore, III",
        "winner": "Democratic",
        "margin": 10107,
        "margin_pct": -14.973333333333333,
        "color": "#6baed6"
      },
      "5": {
        "dem_votes": 55102,
        "rep_votes": 12420,
        "other_votes": 717,
        "total_votes": 68239,
        "dem_candidate": "Mark R. Warner",
        "rep_candidate": "James Jim S. Gilmore, III",
        "winner": "Democratic",
        "margin": 42682,
        "margin_pct": -62.547809903427655,
        "color": "#08306b"
      },
      "6": {
        "dem_votes": 39658,
        "rep_votes": 16659,
        "other_votes": 793,
        "total_votes": 57110,
        "dem_candidate": "Mark R. Warner",
        "rep_candidate": "James Jim S. Gilmore, III",
        "winner": "Democratic",
        "margin": 22999,
        "margin_pct": -40.27140605848363,
        "color": "#08306b"
      },
      "7": {
        "dem_votes": 50669,
        "rep_votes": 28308,
        "other_votes": 1089,
        "total_votes": 80066,
        "dem_candidate": "Mark R. Warner",
        "rep_candidate": "James Jim S. Gilmore, III",
        "winner": "Democratic",
        "margin": 22361,
        "margin_pct": -27.928209227387406,
        "color": "#3182bd"
      },
      "8": {
        "dem_votes": 47498,
        "rep_votes": 27027,
        "other_votes": 1045,
        "total_votes": 75570,
        "dem_candidate": "Mark R. Warner",
        "rep_candidate": "James Jim S. Gilmore, III",
        "winner": "Democratic",
        "margin": 20471,
        "margin_pct": -27.088791848617177,
        "color": "#3182bd"
      },
      "9": {
        "dem_votes": 60400,
        "rep_votes": 15112,
        "other_votes": 996,
        "total_votes": 76508,
        "dem_candidate": "Mark R. Warner",
        "rep_candidate": "James Jim S. Gilmore, III",
        "winner": "Democratic",
        "margin": 45288,
        "margin_pct": -59.193809797668216,
        "color": "#08306b"
      }
    }
  }
}